llama_index/llms/localai/__init__.py
llama_index/llms/localai/base.py
llama_index_llms_localai-0.5.2.dist-info/METADATA
llama_index_llms_localai-0.5.2.dist-info/WHEEL
llama_index_llms_localai-0.5.2.dist-info/licenses/LICENSE
llama_index_llms_localai-0.5.2.dist-info/RECORD
