Metadata-Version: 2.4
Name: llama-index-llms-localai
Version: 0.5.2
Summary: llama-index llms localai integration
Author-email: Your Name <you@example.com>
License-Expression: MIT
License-File: LICENSE
Requires-Python: <4.0,>=3.9
Requires-Dist: llama-index-llms-openai-like<0.6,>=0.5.0
